Workbook

Sheet PROY
A1: PASO 1 — SELECCIÓN DE CLIENTE Y DATOS DEL PROYECTO
A3: Campo / Parámetro | B3: Valor Seleccionado (Presupuestador) | C3: Instrucciones de Captura
A4: Cliente (Seleccionar de Lista) | B4: OH - GABINETES Y AUTOMATIZACION | C4: Selecciona el cliente oficial de la lista desplegable BD
A5: Nombre del Proyecto | B5: INSTALACIÓN Y AUTOMATIZACIÓN DE LÍNEA DE PROCESO | C5: Nombre o concepto técnico oficial del proyecto
A6: Ingeniero Responsable / Presupuestador | B6: DS | C6: Iniciales del presupuestador responsable (ej: DS, RG, JM)
A7: Tipo de Cambio USD (FIX) | B7: 18 | C7: Tipo de cambio aplicable MXN por 1 USD

Sheet WBS
A1: PASO 2 — DEFINICIÓN DE PARTIDAS Y ESTRUCTURA WBS
A3: N° Partida WBS | B3: Nombre / Concepto de la Partida WBS | C3: Alcance General y Especificaciones Técnicas
A4: 1 | B4: Gabinete de Control Principal PLC | C4: Suministro, ensamble y cableado de tablero principal NEMA 12
A5: 2 | B5: Programación de PLC y Pantalla HMI | C5: Desarrollo de lógica de control, pantallas de interfaz HMI y pruebas
A6: 3 | B6: Instalación Eléctrica e Integración en Planta | C6: Tendido de tubería conduit, cableado de campo y puesta en marcha

Sheet 3_MATERIALES
A1: PASO 3.1 — DETALLE DE MATERIALES Y COMPONENTES POR PARTIDA
A3: Partida N° | B3: Partida WBS (Automático) | C3: Concepto / Material | D3: Especificación / Marca | E3: Cantidad | F3: Unidad | G3: Precio Unitario | H3: Moneda (MXN/USD)
A4: 1 | B4: =IFERROR(VLOOKUP(A4, WBS!A$4:B$200, 2, FALSE), "") | C4: PLC CompactLogix 5380 | D4: Allen Bradley 5069-L310ER | E4: 1 | F4: PZA | G4: 2500 | H4: USD
A5: 1 | B5: =IFERROR(VLOOKUP(A5, WBS!A$4:B$200, 2, FALSE), "") | C5: Fuente de Alimentación 24VDC 10A | D5: Phoenix Contact Quint Power | E5: 2 | F5: PZA | G5: 1850 | H5: MXN
A6: 2 | B6: =IFERROR(VLOOKUP(A6, WBS!A$4:B$200, 2, FALSE), "") | C6: Licencia de Software Studio 5000 | D6: Rockwell Automation Professional | E6: 1 | F6: LIC | G6: 3200 | H6: USD
B7: =IFERROR(VLOOKUP(A7, WBS!A$4:B$200, 2, FALSE), "")
B8: =IFERROR(VLOOKUP(A8, WBS!A$4:B$200, 2, FALSE), "")
B9: =IFERROR(VLOOKUP(A9, WBS!A$4:B$200, 2, FALSE), "")
B10: =IFERROR(VLOOKUP(A10, WBS!A$4:B$200, 2, FALSE), "")
B11: =IFERROR(VLOOKUP(A11, WBS!A$4:B$200, 2, FALSE), "")
B12: =IFERROR(VLOOKUP(A12, WBS!A$4:B$200, 2, FALSE), "")
B13: =IFERROR(VLOOKUP(A13, WBS!A$4:B$200, 2, FALSE), "")
B14: =IFERROR(VLOOKUP(A14, WBS!A$4:B$200, 2, FALSE), "")
B15: =IFERROR(VLOOKUP(A15, WBS!A$4:B$200, 2, FALSE), "")
B16: =IFERROR(VLOOKUP(A16, WBS!A$4:B$200, 2, FALSE), "")
B17: =IFERROR(VLOOKUP(A17, WBS!A$4:B$200, 2, FALSE), "")
B18: =IFERROR(VLOOKUP(A18, WBS!A$4:B$200, 2, FALSE), "")
... B199: =IFERROR(VLOOKUP(A199, WBS!A$4:B$200, 2, FALSE), "")

Sheet 4_MANO_DE_OBRA
A1: PASO 3.2 — DETALLE DE MANO DE OBRA (CON SUELDO BASE, FASAR Y COSTO HORA)
A3: Partida N° | B3: Partida WBS (Automático) | C3: Puesto / Categoría (Seleccionar) | D3: Personas | E3: Horas/Día | F3: Días | G3: Sueldo Base Semanal | H3: FASAR % | I3: Costo Hora MXN (Calculado) | J3: Importe Total MO (MXN)
A4: 1 | B4: =IFERROR(VLOOKUP(A4, WBS!A$4:B$200, 2, FALSE), "") | C4: Diseñador de Controles | D4: 1 | E4: 8 | F4: 5 | G4: =IFERROR(VLOOKUP(C4, BD!A$2:C$50, 2, FALSE), 3500) | H4: =IFERROR(VLOOKUP(C4, BD!A$2:C$50, 3, FALSE), 1.45) | I4: =(G4*H4)/48 | J4: =D4*E4*F4*I4
A5: 2 | B5: =IFERROR(VLOOKUP(A5, WBS!A$4:B$200, 2, FALSE), "") | C5: Ingeniero de Control | D5: 1 | E5: 8 | F5: 10 | G5: =IFERROR(VLOOKUP(C5, BD!A$2:C$50, 2, FALSE), 3500) | H5: =IFERROR(VLOOKUP(C5, BD!A$2:C$50, 3, FALSE), 1.45) | I5: =(G5*H5)/48 | J5: =D5*E5*F5*I5
B6: =IFERROR(VLOOKUP(A6, WBS!A$4:B$200, 2, FALSE), "") | G6: =IFERROR(VLOOKUP(C6, BD!A$2:C$50, 2, FALSE), 3500) | H6: =IFERROR(VLOOKUP(C6, BD!A$2:C$50, 3, FALSE), 1.45) | I6: =(G6*H6)/48 | J6: =D6*E6*F6*I6
B7: =IFERROR(VLOOKUP(A7, WBS!A$4:B$200, 2, FALSE), "") | G7: =IFERROR(VLOOKUP(C7, BD!A$2:C$50, 2, FALSE), 3500) | H7: =IFERROR(VLOOKUP(C7, BD!A$2:C$50, 3, FALSE), 1.45) | I7: =(G7*H7)/48 | J7: =D7*E7*F7*I7
B8: =IFERROR(VLOOKUP(A8, WBS!A$4:B$200, 2, FALSE), "") | G8: =IFERROR(VLOOKUP(C8, BD!A$2:C$50, 2, FALSE), 3500) | H8: =IFERROR(VLOOKUP(C8, BD!A$2:C$50, 3, FALSE), 1.45) | I8: =(G8*H8)/48 | J8: =D8*E8*F8*I8
B9: =IFERROR(VLOOKUP(A9, WBS!A$4:B$200, 2, FALSE), "") | G9: =IFERROR(VLOOKUP(C9, BD!A$2:C$50, 2, FALSE), 3500) | H9: =IFERROR(VLOOKUP(C9, BD!A$2:C$50, 3, FALSE), 1.45) | I9: =(G9*H9)/48 | J9: =D9*E9*F9*I9
B10: =IFERROR(VLOOKUP(A10, WBS!A$4:B$200, 2, FALSE), "") | G10: =IFERROR(VLOOKUP(C10, BD!A$2:C$50, 2, FALSE), 3500) | H10: =IFERROR(VLOOKUP(C10, BD!A$2:C$50, 3, FALSE), 1.45) | I10: =(G10*H10)/48 | J10: =D10*E10*F10*I10
B11: =IFERROR(VLOOKUP(A11, WBS!A$4:B$200, 2, FALSE), "") | G11: =IFERROR(VLOOKUP(C11, BD!A$2:C$50, 2, FALSE), 3500) | H11: =IFERROR(VLOOKUP(C11, BD!A$2:C$50, 3, FALSE), 1.45) | I11: =(G11*H11)/48 | J11: =D11*E11*F11*I11
B12: =IFERROR(VLOOKUP(A12, WBS!A$4:B$200, 2, FALSE), "") | G12: =IFERROR(VLOOKUP(C12, BD!A$2:C$50, 2, FALSE), 3500) | H12: =IFERROR(VLOOKUP(C12, BD!A$2:C$50, 3, FALSE), 1.45) | I12: =(G12*H12)/48 | J12: =D12*E12*F12*I12
B13: =IFERROR(VLOOKUP(A13, WBS!A$4:B$200, 2, FALSE), "") | G13: =IFERROR(VLOOKUP(C13, BD!A$2:C$50, 2, FALSE), 3500) | H13: =IFERROR(VLOOKUP(C13, BD!A$2:C$50, 3, FALSE), 1.45) | I13: =(G13*H13)/48 | J13: =D13*E13*F13*I13
B14: =IFERROR(VLOOKUP(A14, WBS!A$4:B$200, 2, FALSE), "") | G14: =IFERROR(VLOOKUP(C14, BD!A$2:C$50, 2, FALSE), 3500) | H14: =IFERROR(VLOOKUP(C14, BD!A$2:C$50, 3, FALSE), 1.45) | I14: =(G14*H14)/48 | J14: =D14*E14*F14*I14
B15: =IFERROR(VLOOKUP(A15, WBS!A$4:B$200, 2, FALSE), "") | G15: =IFERROR(VLOOKUP(C15, BD!A$2:C$50, 2, FALSE), 3500) | H15: =IFERROR(VLOOKUP(C15, BD!A$2:C$50, 3, FALSE), 1.45) | I15: =(G15*H15)/48 | J15: =D15*E15*F15*I15
B16: =IFERROR(VLOOKUP(A16, WBS!A$4:B$200, 2, FALSE), "") | G16: =IFERROR(VLOOKUP(C16, BD!A$2:C$50, 2, FALSE), 3500) | H16: =IFERROR(VLOOKUP(C16, BD!A$2:C$50, 3, FALSE), 1.45) | I16: =(G16*H16)/48 | J16: =D16*E16*F16*I16
B17: =IFERROR(VLOOKUP(A17, WBS!A$4:B$200, 2, FALSE), "") | G17: =IFERROR(VLOOKUP(C17, BD!A$2:C$50, 2, FALSE), 3500) | H17: =IFERROR(VLOOKUP(C17, BD!A$2:C$50, 3, FALSE), 1.45) | I17: =(G17*H17)/48 | J17: =D17*E17*F17*I17
... B199: =IFERROR(VLOOKUP(A199, WBS!A$4:B$200, 2, FALSE), "") | G199: =IFERROR(VLOOKUP(C199, BD!A$2:C$50, 2, FALSE), 3500) | H199: =IFERROR(VLOOKUP(C199, BD!A$2:C$50, 3, FALSE), 1.45) | I199: =(G199*H199)/48 | J199: =D199*E199*F199*I199

Sheet 5_GASTOS_GENERALES
A1: PASO 3.3 — DETALLE DE GASTOS GENERALES DE OBRA POR PARTIDA
A3: Partida N° | B3: Partida WBS (Automático) | C3: Concepto de Gasto (Seleccionar) | D3: Cantidad | E3: Unidad | F3: Tiempo | G3: Costo Unitario | H3: Importe Total (MXN)
A4: 1 | B4: =IFERROR(VLOOKUP(A4, WBS!A$4:B$200, 2, FALSE), "") | C4: Pasajes y Fletes Especiales Obra | D4: 1 | E4: VJE | F4: 5 | G4: 2500 | H4: =D4*F4*G4
A5: 2 | B5: =IFERROR(VLOOKUP(A5, WBS!A$4:B$200, 2, FALSE), "") | C5: Combustibles de Camionetas y Maquinaria | D5: 1 | E5: LOTE | F5: 1 | G5: 3500 | H5: =D5*F5*G5
B6: =IFERROR(VLOOKUP(A6, WBS!A$4:B$200, 2, FALSE), "") | H6: =D6*F6*G6
B7: =IFERROR(VLOOKUP(A7, WBS!A$4:B$200, 2, FALSE), "") | H7: =D7*F7*G7
B8: =IFERROR(VLOOKUP(A8, WBS!A$4:B$200, 2, FALSE), "") | H8: =D8*F8*G8
B9: =IFERROR(VLOOKUP(A9, WBS!A$4:B$200, 2, FALSE), "") | H9: =D9*F9*G9
B10: =IFERROR(VLOOKUP(A10, WBS!A$4:B$200, 2, FALSE), "") | H10: =D10*F10*G10
B11: =IFERROR(VLOOKUP(A11, WBS!A$4:B$200, 2, FALSE), "") | H11: =D11*F11*G11
B12: =IFERROR(VLOOKUP(A12, WBS!A$4:B$200, 2, FALSE), "") | H12: =D12*F12*G12
B13: =IFERROR(VLOOKUP(A13, WBS!A$4:B$200, 2, FALSE), "") | H13: =D13*F13*G13
B14: =IFERROR(VLOOKUP(A14, WBS!A$4:B$200, 2, FALSE), "") | H14: =D14*F14*G14
B15: =IFERROR(VLOOKUP(A15, WBS!A$4:B$200, 2, FALSE), "") | H15: =D15*F15*G15
B16: =IFERROR(VLOOKUP(A16, WBS!A$4:B$200, 2, FALSE), "") | H16: =D16*F16*G16
B17: =IFERROR(VLOOKUP(A17, WBS!A$4:B$200, 2, FALSE), "") | H17: =D17*F17*G17
... B199: =IFERROR(VLOOKUP(A199, WBS!A$4:B$200, 2, FALSE), "") | H199: =D199*F199*G199

Sheet 6_SUBCONTRATOS
A1: PASO 3.4 — DETALLE DE SUBCONTRATOS POR PARTIDA
A3: Partida N° | B3: Partida WBS (Automático) | C3: Concepto Subcontrato (Seleccionar) | D3: Proveedor Habitual | E3: Cantidad | F3: Unidad | G3: Precio Unitario | H3: Moneda | I3: Importe Total MXN
A4: 1 | B4: =IFERROR(VLOOKUP(A4, WBS!A$4:B$200, 2, FALSE), "") | C4: Arrendamiento de Grúa Telescópica | D4: Metalmecánica del Norte | E4: 1 | F4: SERV | G4: 4500 | H4: MXN | I4: =IF(H4="USD", E4*G4*PROY!B$7, E4*G4)
B5: =IFERROR(VLOOKUP(A5, WBS!A$4:B$200, 2, FALSE), "") | I5: =IF(H5="USD", E5*G5*PROY!B$7, E5*G5)
B6: =IFERROR(VLOOKUP(A6, WBS!A$4:B$200, 2, FALSE), "") | I6: =IF(H6="USD", E6*G6*PROY!B$7, E6*G6)
B7: =IFERROR(VLOOKUP(A7, WBS!A$4:B$200, 2, FALSE), "") | I7: =IF(H7="USD", E7*G7*PROY!B$7, E7*G7)
B8: =IFERROR(VLOOKUP(A8, WBS!A$4:B$200, 2, FALSE), "") | I8: =IF(H8="USD", E8*G8*PROY!B$7, E8*G8)
B9: =IFERROR(VLOOKUP(A9, WBS!A$4:B$200, 2, FALSE), "") | I9: =IF(H9="USD", E9*G9*PROY!B$7, E9*G9)
B10: =IFERROR(VLOOKUP(A10, WBS!A$4:B$200, 2, FALSE), "") | I10: =IF(H10="USD", E10*G10*PROY!B$7, E10*G10)
B11: =IFERROR(VLOOKUP(A11, WBS!A$4:B$200, 2, FALSE), "") | I11: =IF(H11="USD", E11*G11*PROY!B$7, E11*G11)
B12: =IFERROR(VLOOKUP(A12, WBS!A$4:B$200, 2, FALSE), "") | I12: =IF(H12="USD", E12*G12*PROY!B$7, E12*G12)
B13: =IFERROR(VLOOKUP(A13, WBS!A$4:B$200, 2, FALSE), "") | I13: =IF(H13="USD", E13*G13*PROY!B$7, E13*G13)
B14: =IFERROR(VLOOKUP(A14, WBS!A$4:B$200, 2, FALSE), "") | I14: =IF(H14="USD", E14*G14*PROY!B$7, E14*G14)
B15: =IFERROR(VLOOKUP(A15, WBS!A$4:B$200, 2, FALSE), "") | I15: =IF(H15="USD", E15*G15*PROY!B$7, E15*G15)
B16: =IFERROR(VLOOKUP(A16, WBS!A$4:B$200, 2, FALSE), "") | I16: =IF(H16="USD", E16*G16*PROY!B$7, E16*G16)
... B199: =IFERROR(VLOOKUP(A199, WBS!A$4:B$200, 2, FALSE), "") | I199: =IF(H199="USD", E199*G199*PROY!B$7, E199*G199)

Sheet 7_MAQUINARIA
A1: PASO 3.5 — DETALLE DE MAQUINARIA Y EQUIPO POR PARTIDA
A3: Partida N° | B3: Partida WBS (Automático) | C3: Concepto Maquinaria / Equipo | D3: Modelo / Capacidad | E3: Tiempo | F3: Unidad | G3: Costo Unitario | H3: Moneda | I3: Importe Total MXN
A4: 3 | B4: =IFERROR(VLOOKUP(A4, WBS!A$4:B$200, 2, FALSE), "") | C4: Renta de Elevador de Tijera 12m | D4: Genie GS-2632 | E4: 5 | F4: DÍA | G4: 1200 | H4: MXN | I4: =IF(H4="USD", E4*G4*PROY!B$7, E4*G4)
B5: =IFERROR(VLOOKUP(A5, WBS!A$4:B$200, 2, FALSE), "") | I5: =IF(H5="USD", E5*G5*PROY!B$7, E5*G5)
B6: =IFERROR(VLOOKUP(A6, WBS!A$4:B$200, 2, FALSE), "") | I6: =IF(H6="USD", E6*G6*PROY!B$7, E6*G6)
B7: =IFERROR(VLOOKUP(A7, WBS!A$4:B$200, 2, FALSE), "") | I7: =IF(H7="USD", E7*G7*PROY!B$7, E7*G7)
B8: =IFERROR(VLOOKUP(A8, WBS!A$4:B$200, 2, FALSE), "") | I8: =IF(H8="USD", E8*G8*PROY!B$7, E8*G8)
B9: =IFERROR(VLOOKUP(A9, WBS!A$4:B$200, 2, FALSE), "") | I9: =IF(H9="USD", E9*G9*PROY!B$7, E9*G9)
B10: =IFERROR(VLOOKUP(A10, WBS!A$4:B$200, 2, FALSE), "") | I10: =IF(H10="USD", E10*G10*PROY!B$7, E10*G10)
B11: =IFERROR(VLOOKUP(A11, WBS!A$4:B$200, 2, FALSE), "") | I11: =IF(H11="USD", E11*G11*PROY!B$7, E11*G11)
B12: =IFERROR(VLOOKUP(A12, WBS!A$4:B$200, 2, FALSE), "") | I12: =IF(H12="USD", E12*G12*PROY!B$7, E12*G12)
B13: =IFERROR(VLOOKUP(A13, WBS!A$4:B$200, 2, FALSE), "") | I13: =IF(H13="USD", E13*G13*PROY!B$7, E13*G13)
B14: =IFERROR(VLOOKUP(A14, WBS!A$4:B$200, 2, FALSE), "") | I14: =IF(H14="USD", E14*G14*PROY!B$7, E14*G14)
B15: =IFERROR(VLOOKUP(A15, WBS!A$4:B$200, 2, FALSE), "") | I15: =IF(H15="USD", E15*G15*PROY!B$7, E15*G15)
B16: =IFERROR(VLOOKUP(A16, WBS!A$4:B$200, 2, FALSE), "") | I16: =IF(H16="USD", E16*G16*PROY!B$7, E16*G16)
... B199: =IFERROR(VLOOKUP(A199, WBS!A$4:B$200, 2, FALSE), "") | I199: =IF(H199="USD", E199*G199*PROY!B$7, E199*G199)

Sheet 4_RESUMEN
A1: PASO 4 — RESUMEN AUTOMÁTICO DE COSTO DIRECTO (TRABAJO DEL PRESUPUESTADOR TERMINADO)
A3: N° Partida | B3: Descripción Partida WBS | C3: Materiales (MXN) | D3: Mano de Obra (MXN) | E3: Gastos Obra (MXN) | F3: Subcontratos (MXN) | G3: Maquinaria (MXN) | H3: TOTAL COSTO DIRECTO (MXN)
A4: 1 | B4: =WBS!B4 | C4: =SUMIF(3_MATERIALES!A$4:A$200, A4, 3_MATERIALES!G$4:G$200) | D4: =SUMIF(4_MANO_DE_OBRA!A$4:A$200, A4, 4_MANO_DE_OBRA!J$4:J$200) | E4: =SUMIF(5_GASTOS_GENERALES!A$4:A$200, A4, 5_GASTOS_GENERALES!H$4:H$200) | F4: =SUMIF(6_SUBCONTRATOS!A$4:A$200, A4, 6_SUBCONTRATOS!I$4:I$200) | G4: =SUMIF(7_MAQUINARIA!A$4:A$200, A4, 7_MAQUINARIA!I$4:I$200) | H4: =SUM(C4:G4)
A5: 2 | B5: =WBS!B5 | C5: =SUMIF(3_MATERIALES!A$4:A$200, A5, 3_MATERIALES!G$4:G$200) | D5: =SUMIF(4_MANO_DE_OBRA!A$4:A$200, A5, 4_MANO_DE_OBRA!J$4:J$200) | E5: =SUMIF(5_GASTOS_GENERALES!A$4:A$200, A5, 5_GASTOS_GENERALES!H$4:H$200) | F5: =SUMIF(6_SUBCONTRATOS!A$4:A$200, A5, 6_SUBCONTRATOS!I$4:I$200) | G5: =SUMIF(7_MAQUINARIA!A$4:A$200, A5, 7_MAQUINARIA!I$4:I$200) | H5: =SUM(C5:G5)
A6: 3 | B6: =WBS!B6 | C6: =SUMIF(3_MATERIALES!A$4:A$200, A6, 3_MATERIALES!G$4:G$200) | D6: =SUMIF(4_MANO_DE_OBRA!A$4:A$200, A6, 4_MANO_DE_OBRA!J$4:J$200) | E6: =SUMIF(5_GASTOS_GENERALES!A$4:A$200, A6, 5_GASTOS_GENERALES!H$4:H$200) | F6: =SUMIF(6_SUBCONTRATOS!A$4:A$200, A6, 6_SUBCONTRATOS!I$4:I$200) | G6: =SUMIF(7_MAQUINARIA!A$4:A$200, A6, 7_MAQUINARIA!I$4:I$200) | H6: =SUM(C6:G6)
B7: TOTAL COSTO DIRECTO DEL PROYECTO: | H7: =SUM(H4:H6)

Sheet BD
A1: PUESTOS_MO | B1: SUELDO_BASE_SEMANAL | C1: FASAR | D1: GASTOS_OBRA | E1: SUBCONTRATOS | F1: CLIENTES
A2: Diseñador de Controles | B2: 5500 | C2: 1.45 | D2: Pasajes y Fletes Especiales Obra | E2: Arrendamiento de Grúa Telescópica | F2: OH - GABINETES Y AUTOMATIZACION
A3: Ingeniero de Control | B3: 5500 | C3: 1.45 | D3: Combustibles de Camionetas y Maquinaria | E3: Corte Láser / Pantógrafo Placas | F3: YESA - YESO Y MOLDURAS
A4: Programador PLC / Robot | B4: 4500 | C4: 1.45 | D4: Comisiones Bancarias por Proyecto | E4: Fabricación de Gabinetes Eléctricos | F4: J&D AUTOMATION INTERNO
A5: Tablerista | B5: 4500 | C5: 1.45 | D5: Hospedaje de Cuadrillas de Obra | E5: Grúa 20 Ton | F5: TREBOTTI
A6: Eléctricos | B6: 3800 | C6: 1.45 | D6: Uniformes y Ropa de Trabajo EPP | E6: Maquinado CNC / Torno de Piezas
A7: Diseñador Mecánico | B7: 3500 | C7: 1.45 | D7: IVA Deducción No Acreditable Obra | E7: Montacargas y Maniobras de Carga
A8: Mecánicos | B8: 3000 | C8: 1.45 | D8: Gastos Médicos y Botiquín de Campo | E8: Pintura Electrostática / Horneado
A9: Montadores | B9: 2800 | C9: 1.45 | D9: Gastos No Deducibles de Obra | E9: Programación Especializada PLC / HMI
A10: Dibujante | B10: 2500 | C10: 1.45 | D10: Mantenimiento a Vehículos de Obra | E10: Pruebas NDT / Ensayos No Destructivos
A11: Ayudantes | B11: 2500 | C11: 1.45 | D11: Adquisiciones Directas para Personal
A12: Supervisor de Obra | B12: 6000 | C12: 1.45 | D12: Viáticos Externos de Campo
D13: Comisionistas y Agentes Externos
D14: Casetas y Peajes de Carretera
D15: Fletes Especializados de Traslado
D16: Herramientas Menores y Refacciones Campo
D17: Maniobras de Carga y Almacén
D18: Agua Potable y Pipas de Obra
D19: Luz y Energía Temporal Obra
D20: Mantenimiento a Equipo Cómputo/Pruebas
D21: Mano de Obra Paga Directa
D22: Honorarios Asimilados a Salarios
D23: Pagos a Mano de Obra Externa
D24: Herramientas y Accesorios de Obra
... D60: Alimentos y Dietas en Campo
