Workbook

Sheet PROY
A1: PASO 1 — SELECCIÓN DE CLIENTE Y DATOS DEL PROYECTO
A3: Campo / Parámetro | B3: Valor (Presupuestador) | C3: Instrucciones de Captura
A4: Cliente (Seleccionar de Lista) | B4: J&D AUTOMATION INTERNO | C4: Selecciona el cliente de la lista desplegable → BD!F
A5: Nombre del Proyecto | B5: AUTOMATIZACIÓN DE LÍNEA DE PROCESO | C5: Nombre técnico oficial del proyecto
A6: Ingeniero Responsable / Presupuestador | B6: DS | C6: Iniciales del presupuestador (ej: DS, RG, JM)
A7: Tipo de Cambio USD (FIX) | B7: 18 | C7: Tipo de cambio MXN por 1 USD para conversiones

Sheet WBS
A1: PASO 2 — DEFINICIÓN DE PARTIDAS Y ESTRUCTURA WBS
A3: N° Partida WBS | B3: Nombre / Concepto de la Partida WBS | C3: Alcance General y Especificaciones Técnicas
A4: 1 | B4: Gabinete de Control Principal PLC | C4: Suministro, ensamble y cableado de tablero principal NEMA 12
A5: 2 | B5: Programación de PLC y Pantalla HMI | C5: Desarrollo de lógica de control, pantallas HMI y pruebas FAT/SAT
A6: 3 | B6: Instalación Eléctrica e Integración en Planta | C6: Tendido de tubería conduit, cableado de campo y puesta en marcha

Sheet MAT
A1: PASO 3.1 — DETALLE DE MATERIALES Y COMPONENTES POR PARTIDA
A3: Partida N° | B3: Partida WBS (Auto) | C3: Concepto / Material | D3: Especificación / Marca | E3: Cantidad | F3: Unidad | G3: Precio Unitario | H3: Moneda (MXN/USD)
A4: 1 | B4: =IFERROR(VLOOKUP(A4,WBS!A$4:B$200,2,FALSE),"") | C4: PLC CompactLogix 5380 | D4: Allen Bradley 5069-L310ER | E4: 1 | F4: PZA | G4: 2500 | H4: USD
A5: 1 | B5: =IFERROR(VLOOKUP(A5,WBS!A$4:B$200,2,FALSE),"") | C5: Fuente de Alimentación 24VDC 10A | D5: Phoenix Contact Quint Power | E5: 2 | F5: PZA | G5: 1850 | H5: MXN
A6: 2 | B6: =IFERROR(VLOOKUP(A6,WBS!A$4:B$200,2,FALSE),"") | C6: Licencia de Software Studio 5000 | D6: Rockwell Automation Professional | E6: 1 | F6: LIC | G6: 3200 | H6: USD
B7: =IFERROR(VLOOKUP(A7,WBS!A$4:B$200,2,FALSE),"")
B8: =IFERROR(VLOOKUP(A8,WBS!A$4:B$200,2,FALSE),"")
B9: =IFERROR(VLOOKUP(A9,WBS!A$4:B$200,2,FALSE),"")
B10: =IFERROR(VLOOKUP(A10,WBS!A$4:B$200,2,FALSE),"")
B11: =IFERROR(VLOOKUP(A11,WBS!A$4:B$200,2,FALSE),"")
B12: =IFERROR(VLOOKUP(A12,WBS!A$4:B$200,2,FALSE),"")
B13: =IFERROR(VLOOKUP(A13,WBS!A$4:B$200,2,FALSE),"")
B14: =IFERROR(VLOOKUP(A14,WBS!A$4:B$200,2,FALSE),"")
B15: =IFERROR(VLOOKUP(A15,WBS!A$4:B$200,2,FALSE),"")
B16: =IFERROR(VLOOKUP(A16,WBS!A$4:B$200,2,FALSE),"")
B17: =IFERROR(VLOOKUP(A17,WBS!A$4:B$200,2,FALSE),"")
B18: =IFERROR(VLOOKUP(A18,WBS!A$4:B$200,2,FALSE),"")
... B199: =IFERROR(VLOOKUP(A199,WBS!A$4:B$200,2,FALSE),"")

Sheet MO
A1: PASO 3.2 — MANO DE OBRA (SUELDO BASE Y FASAR SE ACTUALIZAN AL CAMBIAR EL PUESTO)
A2: 🔵 Las columnas azules (Sueldo Base, FASAR, Costo Hora) se calculan AUTOMÁTICAMENTE desde el Catálogo BD al seleccionar el Puesto
A3: Partida N° | B3: Partida WBS (Auto) | C3: Puesto / Categoría (Seleccionar ▼) | D3: Personas | E3: Horas/Día | F3: Días | G3: Sueldo Base Semanal (BD) | H3: FASAR (BD) | I3: Costo Hora MXN (Auto) | J3: Importe Total MO (MXN)
A4: 1 | B4: =IFERROR(VLOOKUP(A4,WBS!A$4:B$200,2,FALSE),"") | C4: Diseñador de Controles | D4: 1 | E4: 8 | F4: 5 | G4: =IFERROR(VLOOKUP(C4,BD!$A$2:$C$12,2,FALSE),3500) | H4: =IFERROR(VLOOKUP(C4,BD!$A$2:$C$12,3,FALSE),1.45) | I4: =(G4*H4)/48 | J4: =D4*E4*F4*I4
A5: 1 | B5: =IFERROR(VLOOKUP(A5,WBS!A$4:B$200,2,FALSE),"") | C5: Ingeniero de Control | D5: 1 | E5: 8 | F5: 10 | G5: =IFERROR(VLOOKUP(C5,BD!$A$2:$C$12,2,FALSE),3500) | H5: =IFERROR(VLOOKUP(C5,BD!$A$2:$C$12,3,FALSE),1.45) | I5: =(G5*H5)/48 | J5: =D5*E5*F5*I5
A6: 2 | B6: =IFERROR(VLOOKUP(A6,WBS!A$4:B$200,2,FALSE),"") | C6: Programador PLC / Robot | D6: 1 | E6: 8 | F6: 5 | G6: =IFERROR(VLOOKUP(C6,BD!$A$2:$C$12,2,FALSE),3500) | H6: =IFERROR(VLOOKUP(C6,BD!$A$2:$C$12,3,FALSE),1.45) | I6: =(G6*H6)/48 | J6: =D6*E6*F6*I6
B7: =IFERROR(VLOOKUP(A7,WBS!A$4:B$200,2,FALSE),"") | G7: =IFERROR(VLOOKUP(C7,BD!$A$2:$C$12,2,FALSE),"") | H7: =IFERROR(VLOOKUP(C7,BD!$A$2:$C$12,3,FALSE),"") | I7: =IFERROR((G7*H7)/48,"") | J7: =IFERROR(D7*E7*F7*I7,"")
B8: =IFERROR(VLOOKUP(A8,WBS!A$4:B$200,2,FALSE),"") | G8: =IFERROR(VLOOKUP(C8,BD!$A$2:$C$12,2,FALSE),"") | H8: =IFERROR(VLOOKUP(C8,BD!$A$2:$C$12,3,FALSE),"") | I8: =IFERROR((G8*H8)/48,"") | J8: =IFERROR(D8*E8*F8*I8,"")
B9: =IFERROR(VLOOKUP(A9,WBS!A$4:B$200,2,FALSE),"") | G9: =IFERROR(VLOOKUP(C9,BD!$A$2:$C$12,2,FALSE),"") | H9: =IFERROR(VLOOKUP(C9,BD!$A$2:$C$12,3,FALSE),"") | I9: =IFERROR((G9*H9)/48,"") | J9: =IFERROR(D9*E9*F9*I9,"")
B10: =IFERROR(VLOOKUP(A10,WBS!A$4:B$200,2,FALSE),"") | G10: =IFERROR(VLOOKUP(C10,BD!$A$2:$C$12,2,FALSE),"") | H10: =IFERROR(VLOOKUP(C10,BD!$A$2:$C$12,3,FALSE),"") | I10: =IFERROR((G10*H10)/48,"") | J10: =IFERROR(D10*E10*F10*I10,"")
B11: =IFERROR(VLOOKUP(A11,WBS!A$4:B$200,2,FALSE),"") | G11: =IFERROR(VLOOKUP(C11,BD!$A$2:$C$12,2,FALSE),"") | H11: =IFERROR(VLOOKUP(C11,BD!$A$2:$C$12,3,FALSE),"") | I11: =IFERROR((G11*H11)/48,"") | J11: =IFERROR(D11*E11*F11*I11,"")
B12: =IFERROR(VLOOKUP(A12,WBS!A$4:B$200,2,FALSE),"") | G12: =IFERROR(VLOOKUP(C12,BD!$A$2:$C$12,2,FALSE),"") | H12: =IFERROR(VLOOKUP(C12,BD!$A$2:$C$12,3,FALSE),"") | I12: =IFERROR((G12*H12)/48,"") | J12: =IFERROR(D12*E12*F12*I12,"")
B13: =IFERROR(VLOOKUP(A13,WBS!A$4:B$200,2,FALSE),"") | G13: =IFERROR(VLOOKUP(C13,BD!$A$2:$C$12,2,FALSE),"") | H13: =IFERROR(VLOOKUP(C13,BD!$A$2:$C$12,3,FALSE),"") | I13: =IFERROR((G13*H13)/48,"") | J13: =IFERROR(D13*E13*F13*I13,"")
B14: =IFERROR(VLOOKUP(A14,WBS!A$4:B$200,2,FALSE),"") | G14: =IFERROR(VLOOKUP(C14,BD!$A$2:$C$12,2,FALSE),"") | H14: =IFERROR(VLOOKUP(C14,BD!$A$2:$C$12,3,FALSE),"") | I14: =IFERROR((G14*H14)/48,"") | J14: =IFERROR(D14*E14*F14*I14,"")
B15: =IFERROR(VLOOKUP(A15,WBS!A$4:B$200,2,FALSE),"") | G15: =IFERROR(VLOOKUP(C15,BD!$A$2:$C$12,2,FALSE),"") | H15: =IFERROR(VLOOKUP(C15,BD!$A$2:$C$12,3,FALSE),"") | I15: =IFERROR((G15*H15)/48,"") | J15: =IFERROR(D15*E15*F15*I15,"")
B16: =IFERROR(VLOOKUP(A16,WBS!A$4:B$200,2,FALSE),"") | G16: =IFERROR(VLOOKUP(C16,BD!$A$2:$C$12,2,FALSE),"") | H16: =IFERROR(VLOOKUP(C16,BD!$A$2:$C$12,3,FALSE),"") | I16: =IFERROR((G16*H16)/48,"") | J16: =IFERROR(D16*E16*F16*I16,"")
B17: =IFERROR(VLOOKUP(A17,WBS!A$4:B$200,2,FALSE),"") | G17: =IFERROR(VLOOKUP(C17,BD!$A$2:$C$12,2,FALSE),"") | H17: =IFERROR(VLOOKUP(C17,BD!$A$2:$C$12,3,FALSE),"") | I17: =IFERROR((G17*H17)/48,"") | J17: =IFERROR(D17*E17*F17*I17,"")
B18: =IFERROR(VLOOKUP(A18,WBS!A$4:B$200,2,FALSE),"") | G18: =IFERROR(VLOOKUP(C18,BD!$A$2:$C$12,2,FALSE),"") | H18: =IFERROR(VLOOKUP(C18,BD!$A$2:$C$12,3,FALSE),"") | I18: =IFERROR((G18*H18)/48,"") | J18: =IFERROR(D18*E18*F18*I18,"")
... B199: =IFERROR(VLOOKUP(A199,WBS!A$4:B$200,2,FALSE),"") | G199: =IFERROR(VLOOKUP(C199,BD!$A$2:$C$12,2,FALSE),"") | H199: =IFERROR(VLOOKUP(C199,BD!$A$2:$C$12,3,FALSE),"") | I199: =IFERROR((G199*H199)/48,"") | J199: =IFERROR(D199*E199*F199*I199,"")

Sheet GAS
A1: PASO 3.3 — GASTOS GENERALES DE OBRA (GLOBALES — SE PRORRATEAN ENTRE PARTIDAS EN EL RESUMEN)
A2: 📌 No asignar a partida. El costo total se distribuirá automáticamente entre todas las partidas según su % de costo directo.
A3: Concepto de Gasto (Seleccionar ▼) | B3: Cantidad | C3: Unidad | D3: Tiempo | E3: Costo Unitario | F3: IMPORTE TOTAL (MXN)
A4: Pasajes y Fletes Especiales Obra | B4: 1 | C4: VJE | D4: 5 | E4: 1200 | F4: =B4*D4*E4
A5: Combustibles de Camionetas y Maquinaria | B5: 1 | C5: VJE | D5: 1 | E5: 1500 | F5: =B5*D5*E5
F6: =IFERROR(B6*D6*E6,"")
F7: =IFERROR(B7*D7*E7,"")
F8: =IFERROR(B8*D8*E8,"")
F9: =IFERROR(B9*D9*E9,"")
F10: =IFERROR(B10*D10*E10,"")
F11: =IFERROR(B11*D11*E11,"")
F12: =IFERROR(B12*D12*E12,"")
F13: =IFERROR(B13*D13*E13,"")
F14: =IFERROR(B14*D14*E14,"")
F15: =IFERROR(B15*D15*E15,"")
F16: =IFERROR(B16*D16*E16,"")
F17: =IFERROR(B17*D17*E17,"")
... F199: =IFERROR(B199*D199*E199,"")
A200: TOTAL GASTOS GENERALES DEL PROYECTO: | F200: =SUM(F4:F199)

Sheet SUB
A1: PASO 3.4 — DETALLE DE SUBCONTRATOS POR PARTIDA
A3: Partida N° | B3: Partida WBS (Auto) | C3: Concepto Subcontrato (Seleccionar ▼) | D3: Proveedor Habitual | E3: Cantidad | F3: Unidad | G3: Precio Unitario | H3: Moneda | I3: Importe Total MXN
A4: 1 | B4: =IFERROR(VLOOKUP(A4,WBS!A$4:B$200,2,FALSE),"") | C4: Arrendamiento de Grúa Telescópica | D4: Alquiler Grúas | E4: 1 | F4: SERV | G4: 8500 | H4: MXN | I4: =IF(H4="USD",E4*G4*PROY!$B$7,E4*G4)
B5: =IFERROR(VLOOKUP(A5,WBS!A$4:B$200,2,FALSE),"") | I5: =IFERROR(IF(H5="USD",E5*G5*PROY!$B$7,E5*G5),"")
B6: =IFERROR(VLOOKUP(A6,WBS!A$4:B$200,2,FALSE),"") | I6: =IFERROR(IF(H6="USD",E6*G6*PROY!$B$7,E6*G6),"")
B7: =IFERROR(VLOOKUP(A7,WBS!A$4:B$200,2,FALSE),"") | I7: =IFERROR(IF(H7="USD",E7*G7*PROY!$B$7,E7*G7),"")
B8: =IFERROR(VLOOKUP(A8,WBS!A$4:B$200,2,FALSE),"") | I8: =IFERROR(IF(H8="USD",E8*G8*PROY!$B$7,E8*G8),"")
B9: =IFERROR(VLOOKUP(A9,WBS!A$4:B$200,2,FALSE),"") | I9: =IFERROR(IF(H9="USD",E9*G9*PROY!$B$7,E9*G9),"")
B10: =IFERROR(VLOOKUP(A10,WBS!A$4:B$200,2,FALSE),"") | I10: =IFERROR(IF(H10="USD",E10*G10*PROY!$B$7,E10*G10),"")
B11: =IFERROR(VLOOKUP(A11,WBS!A$4:B$200,2,FALSE),"") | I11: =IFERROR(IF(H11="USD",E11*G11*PROY!$B$7,E11*G11),"")
B12: =IFERROR(VLOOKUP(A12,WBS!A$4:B$200,2,FALSE),"") | I12: =IFERROR(IF(H12="USD",E12*G12*PROY!$B$7,E12*G12),"")
B13: =IFERROR(VLOOKUP(A13,WBS!A$4:B$200,2,FALSE),"") | I13: =IFERROR(IF(H13="USD",E13*G13*PROY!$B$7,E13*G13),"")
B14: =IFERROR(VLOOKUP(A14,WBS!A$4:B$200,2,FALSE),"") | I14: =IFERROR(IF(H14="USD",E14*G14*PROY!$B$7,E14*G14),"")
B15: =IFERROR(VLOOKUP(A15,WBS!A$4:B$200,2,FALSE),"") | I15: =IFERROR(IF(H15="USD",E15*G15*PROY!$B$7,E15*G15),"")
B16: =IFERROR(VLOOKUP(A16,WBS!A$4:B$200,2,FALSE),"") | I16: =IFERROR(IF(H16="USD",E16*G16*PROY!$B$7,E16*G16),"")
... B199: =IFERROR(VLOOKUP(A199,WBS!A$4:B$200,2,FALSE),"") | I199: =IFERROR(IF(H199="USD",E199*G199*PROY!$B$7,E199*G199),"")

Sheet MAQ
A1: PASO 3.5 — DETALLE DE MAQUINARIA Y EQUIPO POR PARTIDA
A3: Partida N° | B3: Partida WBS (Auto) | C3: Concepto Maquinaria / Equipo (Seleccionar ▼) | D3: Modelo / Capacidad | E3: Tiempo | F3: Unidad | G3: Costo Unitario | H3: Moneda | I3: Importe Total MXN
A4: 1 | B4: =IFERROR(VLOOKUP(A4,WBS!A$4:B$200,2,FALSE),"") | C4: Combustibles de Camionetas y Maquinaria | D4: — | E4: 5 | F4: DÍA | G4: 1500 | H4: MXN | I4: =IF(H4="USD",E4*G4*PROY!$B$7,E4*G4)
B5: =IFERROR(VLOOKUP(A5,WBS!A$4:B$200,2,FALSE),"") | I5: =IFERROR(IF(H5="USD",E5*G5*PROY!$B$7,E5*G5),"")
B6: =IFERROR(VLOOKUP(A6,WBS!A$4:B$200,2,FALSE),"") | I6: =IFERROR(IF(H6="USD",E6*G6*PROY!$B$7,E6*G6),"")
B7: =IFERROR(VLOOKUP(A7,WBS!A$4:B$200,2,FALSE),"") | I7: =IFERROR(IF(H7="USD",E7*G7*PROY!$B$7,E7*G7),"")
B8: =IFERROR(VLOOKUP(A8,WBS!A$4:B$200,2,FALSE),"") | I8: =IFERROR(IF(H8="USD",E8*G8*PROY!$B$7,E8*G8),"")
B9: =IFERROR(VLOOKUP(A9,WBS!A$4:B$200,2,FALSE),"") | I9: =IFERROR(IF(H9="USD",E9*G9*PROY!$B$7,E9*G9),"")
B10: =IFERROR(VLOOKUP(A10,WBS!A$4:B$200,2,FALSE),"") | I10: =IFERROR(IF(H10="USD",E10*G10*PROY!$B$7,E10*G10),"")
B11: =IFERROR(VLOOKUP(A11,WBS!A$4:B$200,2,FALSE),"") | I11: =IFERROR(IF(H11="USD",E11*G11*PROY!$B$7,E11*G11),"")
B12: =IFERROR(VLOOKUP(A12,WBS!A$4:B$200,2,FALSE),"") | I12: =IFERROR(IF(H12="USD",E12*G12*PROY!$B$7,E12*G12),"")
B13: =IFERROR(VLOOKUP(A13,WBS!A$4:B$200,2,FALSE),"") | I13: =IFERROR(IF(H13="USD",E13*G13*PROY!$B$7,E13*G13),"")
B14: =IFERROR(VLOOKUP(A14,WBS!A$4:B$200,2,FALSE),"") | I14: =IFERROR(IF(H14="USD",E14*G14*PROY!$B$7,E14*G14),"")
B15: =IFERROR(VLOOKUP(A15,WBS!A$4:B$200,2,FALSE),"") | I15: =IFERROR(IF(H15="USD",E15*G15*PROY!$B$7,E15*G15),"")
B16: =IFERROR(VLOOKUP(A16,WBS!A$4:B$200,2,FALSE),"") | I16: =IFERROR(IF(H16="USD",E16*G16*PROY!$B$7,E16*G16),"")
... B199: =IFERROR(VLOOKUP(A199,WBS!A$4:B$200,2,FALSE),"") | I199: =IFERROR(IF(H199="USD",E199*G199*PROY!$B$7,E199*G199),"")

Sheet PLAN
A1: PASO 3.6 — CRONOGRAMA DE GANTT Y PLAN DE PROYECTO
A2: 📌 Detalla las actividades del proyecto. La columna D muestra un calendario flotante. La columna G busca la partida y la columna I define predecesoras. El Gantt se dibuja automáticamente en columnas J en adelante. | J2: =UPPER(TEXT(J3, "MMMM YYYY")) | K2: =IF(MONTH(K3)<>MONTH(J3), UPPER(TEXT(K3, "MMMM YYYY")), "") | L2: =IF(MONTH(L3)<>MONTH(K3), UPPER(TEXT(L3, "MMMM YYYY")), "") | M2: =IF(MONTH(M3)<>MONTH(L3), UPPER(TEXT(M3, "MMMM YYYY")), "") | N2: =IF(MONTH(N3)<>MONTH(M3), UPPER(TEXT(N3, "MMMM YYYY")), "") | O2: =IF(MONTH(O3)<>MONTH(N3), UPPER(TEXT(O3, "MMMM YYYY")), "") | P2: =IF(MONTH(P3)<>MONTH(O3), UPPER(TEXT(P3, "MMMM YYYY")), "") | Q2: =IF(MONTH(Q3)<>MONTH(P3), UPPER(TEXT(Q3, "MMMM YYYY")), "") | R2: =IF(MONTH(R3)<>MONTH(Q3), UPPER(TEXT(R3, "MMMM YYYY")), "") | ... BC2: =IF(MONTH(BC3)<>MONTH(BB3), UPPER(TEXT(BC3, "MMMM YYYY")), "")
A3: N° Tarea | B3: Tipo de Tarea | C3: Ing. Responsable / Rol | D3: Fecha de Inicio (AAAA-MM-DD) | E3: Duración (Días) | F3: Asociar a Partida N° | G3: Partida WBS (Auto) | H3: Descripción de la Actividad | I3: Predecesoras | J3: =D4 | K3: =J3+1 | L3: =K3+1 | M3: =L3+1 | N3: =M3+1 | O3: =N3+1 | P3: =O3+1 | Q3: =P3+1 | R3: =Q3+1 | ... BC3: =BB3+1
A4: 1 | B4: Actividad | C4: DS | D4: 46245 | E4: 5 | F4: 1 | G4: =IFERROR(VLOOKUP(F4, WBS!A$4:B$200, 2, FALSE), "") | H4: Levantamiento y validación técnica en sitio
A5: 2 | B5: Entregable | C5: DS | D5: =IF(OR(ISBLANK(I5), I5=""), $D$4, INDEX(D$4:D$200, MATCH(I5, A$4:A$200, 0)) + INDEX(E$4:E$200, MATCH(I5, A$4:A$200, 0))) | E5: 7 | F5: 1 | G5: =IFERROR(VLOOKUP(F5, WBS!A$4:B$200, 2, FALSE), "") | H5: Diseño tridimensional y diagramas eléctricos | I5: 1
A6: 3 | B6: Reunión | C6: DS | D6: =IF(OR(ISBLANK(I6), I6=""), $D$4, INDEX(D$4:D$200, MATCH(I6, A$4:A$200, 0)) + INDEX(E$4:E$200, MATCH(I6, A$4:A$200, 0))) | E6: 1 | F6: 2 | G6: =IFERROR(VLOOKUP(F6, WBS!A$4:B$200, 2, FALSE), "") | H6: Reunión de revisión de ingeniería con cliente | I6: 2
A7: 4 | B7: Hito | C7: DS | D7: =IF(OR(ISBLANK(I7), I7=""), $D$4, INDEX(D$4:D$200, MATCH(I7, A$4:A$200, 0)) + INDEX(E$4:E$200, MATCH(I7, A$4:A$200, 0))) | E7: 1 | F7: 2 | G7: =IFERROR(VLOOKUP(F7, WBS!A$4:B$200, 2, FALSE), "") | H7: Hito: Aprobación final de diseño para manufactura | I7: 3
A8: 5 | D8: =IF(OR(ISBLANK(I8), I8=""), $D$4, INDEX(D$4:D$200, MATCH(I8, A$4:A$200, 0)) + INDEX(E$4:E$200, MATCH(I8, A$4:A$200, 0))) | G8: =IFERROR(VLOOKUP(F8, WBS!A$4:B$200, 2, FALSE), "")
A9: 6 | D9: =IF(OR(ISBLANK(I9), I9=""), $D$4, INDEX(D$4:D$200, MATCH(I9, A$4:A$200, 0)) + INDEX(E$4:E$200, MATCH(I9, A$4:A$200, 0))) | G9: =IFERROR(VLOOKUP(F9, WBS!A$4:B$200, 2, FALSE), "")
A10: 7 | D10: =IF(OR(ISBLANK(I10), I10=""), $D$4, INDEX(D$4:D$200, MATCH(I10, A$4:A$200, 0)) + INDEX(E$4:E$200, MATCH(I10, A$4:A$200, 0))) | G10: =IFERROR(VLOOKUP(F10, WBS!A$4:B$200, 2, FALSE), "")
A11: 8 | D11: =IF(OR(ISBLANK(I11), I11=""), $D$4, INDEX(D$4:D$200, MATCH(I11, A$4:A$200, 0)) + INDEX(E$4:E$200, MATCH(I11, A$4:A$200, 0))) | G11: =IFERROR(VLOOKUP(F11, WBS!A$4:B$200, 2, FALSE), "")
A12: 9 | D12: =IF(OR(ISBLANK(I12), I12=""), $D$4, INDEX(D$4:D$200, MATCH(I12, A$4:A$200, 0)) + INDEX(E$4:E$200, MATCH(I12, A$4:A$200, 0))) | G12: =IFERROR(VLOOKUP(F12, WBS!A$4:B$200, 2, FALSE), "")
A13: 10 | D13: =IF(OR(ISBLANK(I13), I13=""), $D$4, INDEX(D$4:D$200, MATCH(I13, A$4:A$200, 0)) + INDEX(E$4:E$200, MATCH(I13, A$4:A$200, 0))) | G13: =IFERROR(VLOOKUP(F13, WBS!A$4:B$200, 2, FALSE), "")
A14: 11 | D14: =IF(OR(ISBLANK(I14), I14=""), $D$4, INDEX(D$4:D$200, MATCH(I14, A$4:A$200, 0)) + INDEX(E$4:E$200, MATCH(I14, A$4:A$200, 0))) | G14: =IFERROR(VLOOKUP(F14, WBS!A$4:B$200, 2, FALSE), "")
A15: 12 | D15: =IF(OR(ISBLANK(I15), I15=""), $D$4, INDEX(D$4:D$200, MATCH(I15, A$4:A$200, 0)) + INDEX(E$4:E$200, MATCH(I15, A$4:A$200, 0))) | G15: =IFERROR(VLOOKUP(F15, WBS!A$4:B$200, 2, FALSE), "")
A16: 13 | D16: =IF(OR(ISBLANK(I16), I16=""), $D$4, INDEX(D$4:D$200, MATCH(I16, A$4:A$200, 0)) + INDEX(E$4:E$200, MATCH(I16, A$4:A$200, 0))) | G16: =IFERROR(VLOOKUP(F16, WBS!A$4:B$200, 2, FALSE), "")
A17: 14 | D17: =IF(OR(ISBLANK(I17), I17=""), $D$4, INDEX(D$4:D$200, MATCH(I17, A$4:A$200, 0)) + INDEX(E$4:E$200, MATCH(I17, A$4:A$200, 0))) | G17: =IFERROR(VLOOKUP(F17, WBS!A$4:B$200, 2, FALSE), "")
A18: 15 | D18: =IF(OR(ISBLANK(I18), I18=""), $D$4, INDEX(D$4:D$200, MATCH(I18, A$4:A$200, 0)) + INDEX(E$4:E$200, MATCH(I18, A$4:A$200, 0))) | G18: =IFERROR(VLOOKUP(F18, WBS!A$4:B$200, 2, FALSE), "")
A19: 16 | D19: =IF(OR(ISBLANK(I19), I19=""), $D$4, INDEX(D$4:D$200, MATCH(I19, A$4:A$200, 0)) + INDEX(E$4:E$200, MATCH(I19, A$4:A$200, 0))) | G19: =IFERROR(VLOOKUP(F19, WBS!A$4:B$200, 2, FALSE), "")
... A199: 196 | D199: =IF(OR(ISBLANK(I199), I199=""), $D$4, INDEX(D$4:D$200, MATCH(I199, A$4:A$200, 0)) + INDEX(E$4:E$200, MATCH(I199, A$4:A$200, 0))) | G199: =IFERROR(VLOOKUP(F199, WBS!A$4:B$200, 2, FALSE), "")

Sheet RESUMEN DE COSTO
A1: PASO 4 — RESUMEN DE COSTO DIRECTO CON PRORRATEO DE GASTOS GENERALES
A2: 🟠 Los Gastos Generales (GAS) se prorratean entre partidas según su % del Costo Directo Base (MAT+MO+SUB+MAQ)
A3: N° Partida | B3: Descripción Partida WBS | C3: Materiales (MXN) | D3: Mano de Obra (MXN) | E3: Subcontratos (MXN) | F3: Maquinaria (MXN) | G3: Costo Directo Base | H3: % sobre Total | I3: GAS Prorrateado (MXN) | J3: TOTAL CON GASTOS (MXN)
A4: 1 | B4: =WBS!B4 | C4: =SUMIF(MAT!A$4:A$200,A4,MAT!G$4:G$200) | D4: =SUMIF(MO!A$4:A$200,A4,MO!J$4:J$200) | E4: =SUMIF(SUB!A$4:A$200,A4,SUB!I$4:I$200) | F4: =SUMIF(MAQ!A$4:A$200,A4,MAQ!I$4:I$200) | G4: =SUM(C4:F4) | H4: =IFERROR(G4/SUM($G$4:$G$6),0) | I4: =GAS!$F$200 * H4 | J4: =G4+I4
A5: 2 | B5: =WBS!B5 | C5: =SUMIF(MAT!A$4:A$200,A5,MAT!G$4:G$200) | D5: =SUMIF(MO!A$4:A$200,A5,MO!J$4:J$200) | E5: =SUMIF(SUB!A$4:A$200,A5,SUB!I$4:I$200) | F5: =SUMIF(MAQ!A$4:A$200,A5,MAQ!I$4:I$200) | G5: =SUM(C5:F5) | H5: =IFERROR(G5/SUM($G$4:$G$6),0) | I5: =GAS!$F$200 * H5 | J5: =G5+I5
A6: 3 | B6: =WBS!B6 | C6: =SUMIF(MAT!A$4:A$200,A6,MAT!G$4:G$200) | D6: =SUMIF(MO!A$4:A$200,A6,MO!J$4:J$200) | E6: =SUMIF(SUB!A$4:A$200,A6,SUB!I$4:I$200) | F6: =SUMIF(MAQ!A$4:A$200,A6,MAQ!I$4:I$200) | G6: =SUM(C6:F6) | H6: =IFERROR(G6/SUM($G$4:$G$6),0) | I6: =GAS!$F$200 * H6 | J6: =G6+I6
B7: TOTALES: | C7: =SUM(C4:C6) | D7: =SUM(D4:D6) | E7: =SUM(E4:E6) | F7: =SUM(F4:F6) | G7: =SUM(G4:G6) | H7: =SUM(H4:H6) | I7: =GAS!$F$200 | J7: =SUM(J4:J6)
B9: * GAS!F200 = Celda TOTAL de la hoja GAS (suma de todos los Gastos Generales del proyecto)
B10: * % sobre Total = Costo Directo Base de la partida / Total Costo Directo Base del proyecto
B11: * GAS Prorrateado = Total GAS × %, distribuyendo el gasto general de forma proporcional al peso de cada partida

Sheet BD
A1: PUESTOS_MO | B1: SUELDO_BASE | C1: FASAR | D1: GASTOS_OBRA | E1: SUBCONTRATOS | F1: MAQ_EQUIPO | G1: CLIENTES
A2: Diseñador de Controles | B2: 5500 | C2: 1.45 | D2: Pasajes y Fletes Especiales Obra | E2: Arrendamiento de Grúa Telescópica | F2: Combustibles de Camionetas y Maquinaria | G2: J&D AUTOMATION INTERNO
A3: Ingeniero de Control | B3: 5500 | C3: 1.45 | D3: Combustibles de Camionetas y Maquinaria | E3: Corte Láser / Pantógrafo Placas | F3: Mantenimiento a Equipo Cómputo/Pruebas | G3: OH - GABINETES Y AUTOMATIZACION
A4: Programador PLC / Robot | B4: 4500 | C4: 1.45 | D4: Comisiones Bancarias por Proyecto | E4: Fabricación de Gabinetes Eléctricos | F4: Arrendamiento de Equipo y Herramienta | G4: TREBOTTI
A5: Tablerista | B5: 4500 | C5: 1.45 | D5: Hospedaje de Cuadrillas de Obra | E5: Grúa 20 Ton | F5: Hospedaje y Renta de Personal | G5: YESA - YESO Y MOLDURAS
A6: Eléctricos | B6: 3800 | C6: 1.45 | D6: Uniformes y Ropa de Trabajo EPP | E6: Maquinado CNC / Torno de Piezas | F6: Maquinaria y Equipo Menor de Obra
A7: Diseñador Mecánico | B7: 3500 | C7: 1.45 | D7: IVA Deducción No Acreditable Obra | E7: Montacargas y Maniobras de Carga | F7: Renta de Mediciones e Instrumentos
A8: Mecánicos | B8: 3000 | C8: 1.45 | D8: Gastos Médicos y Botiquín de Campo | E8: Pintura Electrostática / Horneado | F8: Seguros de Equipo y Pólizas de Propiedad
A9: Montadores | B9: 2800 | C9: 1.45 | D9: Gastos No Deducibles de Obra | E9: Programación Especializada PLC / HMI | F9: Fletes de Materiales y Equipos
A10: Dibujante | B10: 2500 | C10: 1.45 | D10: Mantenimiento a Vehículos de Obra | E10: Pruebas NDT / Ensayos No Destructivos | F10: Combustible para Vehículos y Equipos
A11: Ayudantes | B11: 2500 | C11: 1.45 | D11: Adquisiciones Directas para Personal
A12: Supervisor de Obra | B12: 6000 | C12: 1.45 | D12: Viáticos Externos de Campo
D13: Comisionistas y Agentes Externos
D14: Casetas y Peajes de Carretera
D15: Fletes Especializados de Traslado
D16: Herramientas Menores y Refacciones Campo
D17: Maniobras de Carga y Almacén
D18: Agua Potable y Pipas de Obra
D19: Luz y Energía Temporal Obra
D20: Mantenimiento a Equipo Cómputo/Pruebas
D21: Mano de Obra Paga Directa
D22: Honorarios Asimilados a Salarios
D23: Pagos a Mano de Obra Externa
D24: Herramientas y Accesorios de Obra
... D60: Alimentos y Dietas en Campo
